chimera/__init__.py
chimera/__main__.py
chimera/chimera.py
chimera/config_manager.py
chimera/parcellation.py
chimera/processing.py
chimera/config/__init__.py
chimera/config/pipe_config.json
chimera/config/supraregions_dictionary.json
chimera/config/supraregions/Amygdala.tsv
chimera/config/supraregions/AuxiliaryLUTTable.tsv
chimera/config/supraregions/Brainstem.tsv
chimera/config/supraregions/Cerebellum.tsv
chimera/config/supraregions/Hippocampus.tsv
chimera/config/supraregions/Hypothalamus.tsv
chimera/config/supraregions/Subcortical.tsv
chimera/config/supraregions/Thalamus.tsv
chimera/config/supraregions/WhiteMatter.tsv
chimera/config/supraregions/__init__.py
chimera/data/__init__.py
chimera/data/annot_atlases/__init__.py
chimera/data/annot_atlases/tpl-fsaverage_hemi-L_den-164k_atlas-Lausanne2018_scale-1_dseg.label.annot
chimera/data/annot_atlases/tpl-fsaverage_hemi-L_den-164k_atlas-Lausanne2018_scale-2_dseg.label.annot
chimera/data/annot_atlases/tpl-fsaverage_hemi-L_den-164k_atlas-Lausanne2018_scale-3_dseg.label.annot
chimera/data/annot_atlases/tpl-fsaverage_hemi-L_den-164k_atlas-Lausanne2018_scale-4_dseg.label.annot
chimera/data/annot_atlases/tpl-fsaverage_hemi-L_den-164k_atlas-Lausanne2018_scale-5_dseg.label.annot
chimera/data/annot_atlases/tpl-fsaverage_hemi-L_den-164k_atlas-Schaefer2018_seg-17n_scale-1000_dseg.label.annot
chimera/data/annot_atlases/tpl-fsaverage_hemi-L_den-164k_atlas-Schaefer2018_seg-17n_scale-100_dseg.label.annot
chimera/data/annot_atlases/tpl-fsaverage_hemi-L_den-164k_atlas-Schaefer2018_seg-17n_scale-200_dseg.label.annot
chimera/data/annot_atlases/tpl-fsaverage_hemi-L_den-164k_atlas-Schaefer2018_seg-17n_scale-300_dseg.label.annot
chimera/data/annot_atlases/tpl-fsaverage_hemi-L_den-164k_atlas-Schaefer2018_seg-17n_scale-400_dseg.label.annot
chimera/data/annot_atlases/tpl-fsaverage_hemi-L_den-164k_atlas-Schaefer2018_seg-17n_scale-500_dseg.label.annot
chimera_brainparcellation-0.2.1.dist-info/licenses/AUTHORS.rst
chimera_brainparcellation-0.2.1.dist-info/licenses/LICENSE
chimera_brainparcellation-0.2.1.dist-info/METADATA
chimera_brainparcellation-0.2.1.dist-info/WHEEL
chimera_brainparcellation-0.2.1.dist-info/entry_points.txt
chimera_brainparcellation-0.2.1.dist-info/top_level.txt
chimera_brainparcellation-0.2.1.dist-info/RECORD
