Metadata-Version: 2.4
Name: chimera-brainparcellation
Version: 0.2.1
Summary: An open source framework for combining multiple parcellations of the human brain
Author-email: Yasser Aleman Gomez <yasseraleman@protonmail.com>
License: Apache-2.0
Project-URL: Homepage, https://github.com/yasseraleman/chimera
Project-URL: Repository, https://github.com/yasseraleman/chimera
Project-URL: Documentation, https://chimera.readthedocs.io
Project-URL: Bug Reports, https://github.com/yasseraleman/chimera/issues
Classifier: Development Status :: 3 - Alpha
Classifier: Intended Audience :: Science/Research
Classifier: License :: OSI Approved :: Apache Software License
Classifier: Natural Language :: English
Classifier: Programming Language :: Python :: 3
Classifier: Programming Language :: Python :: 3.9
Classifier: Programming Language :: Python :: 3.10
Classifier: Programming Language :: Python :: 3.11
Classifier: Programming Language :: Python :: 3.12
Classifier: Topic :: Scientific/Engineering :: Medical Science Apps.
Classifier: Topic :: Scientific/Engineering :: Image Processing
Requires-Python: >=3.9
License-File: LICENSE
License-File: AUTHORS.rst
Requires-Dist: numpy>=1.21.0
Requires-Dist: scipy>=1.7.0
Requires-Dist: pandas>=1.3.0
Requires-Dist: nibabel>=3.2.0
Requires-Dist: pybids>=0.15.0
Requires-Dist: templateflow>=0.8.0
Requires-Dist: clabtoolkit>=0.3.0
Requires-Dist: rich>=10.0.0
Provides-Extra: dev
Requires-Dist: pytest>=6.0; extra == "dev"
Requires-Dist: pytest-cov>=2.0; extra == "dev"
Requires-Dist: black>=22.0; extra == "dev"
Requires-Dist: ruff>=0.0.200; extra == "dev"
Requires-Dist: mypy>=0.900; extra == "dev"
Requires-Dist: pre-commit>=2.15; extra == "dev"
Provides-Extra: docs
Requires-Dist: sphinx>=4.0; extra == "docs"
Requires-Dist: sphinx-rtd-theme>=1.0; extra == "docs"
Requires-Dist: sphinx-autodoc-typehints>=1.12; extra == "docs"
Requires-Dist: m2r2>=0.3.0; extra == "docs"
Dynamic: license-file
